bab/__init__.py
bab/make_data.py
bab/mcmc.py
bab/model.py
bab/model.stan
bab/power.py
bab/stan_utils.py
bab/utils.py
bab-0.1.4.dist-info/LICENSE
bab-0.1.4.dist-info/METADATA
bab-0.1.4.dist-info/WHEEL
bab-0.1.4.dist-info/top_level.txt
bab-0.1.4.dist-info/RECORD
